[{"yr":2017,"no":1,"country":"한국","designer":"박지훈, 윤성서 (Park Jihoon, Yoon Sungseo)","title":"쓰기의 연대기（Chronicle of Writing）","file":"5_1.jpg"},
{"yr":2017,"no":2,"country":"한국","designer":"전가경（Jun Kakyung）","title":"쓰기의 현재（The Present Time of Lettering and Drawing Letters）","file":"5_2.jpg"},
{"yr":2017,"no":3,"country":"한국","designer":"문장현, 제너럴그래픽스 (Moon Janghyun, generalgraphics)","title":"쓰기 너머（Beyond Writing）","file":"5_3.jpg"},
{"yr":2017,"no":4,"country":"한국","designer":"한정훈（Han Jeonghoon）","title":"AKA.성운아（AKA. Sung Un A*）","file":"5_4.jpg"},
{"yr":2017,"no":5,"country":"한국","designer":"신믿음, 조별（Shin Mideum, Cho Byul）","title":"디지타이즈드 핸드라이팅（Digitized Handwriting）","file":"5_5.jpg"},
{"yr":2017,"no":6,"country":"한국","designer":"손범영（Sohn Beomyoung）","title":"딜리버（Deliver）","file":"5_6.jpg"},
{"yr":2017,"no":7,"country":"한국","designer":"서울로（SEOULRO）","title":"존경（Respect）","file":"5_7.jpg"},
{"yr":2017,"no":8,"country":"한국","designer":"골든트리（Golden Tree）","title":"모노리스 인 레드（Monolith in Red）","file":"5_8.jpg"},
{"yr":2017,"no":9,"country":"한국","designer":"60603","title":"주체할 수 없는 물결（Irresistible wave）","file":"5_9.jpg"},
{"yr":2017,"no":10,"country":"한국","designer":"최유진（Choi Youjin）","title":"가벼운 살（Weak skin）","file":"5_10.jpg"},
{"yr":2017,"no":11,"country":"한국","designer":"함준서（Hahm Junseo）","title":"생물 문자（Life_forms and Letters）","file":"5_11.jpg"},
{"yr":2017,"no":12,"country":"한국","designer":"이인수（Lee Insu）","title":"몸_언어（Body_Language）","file":"5_12.jpg"},
{"yr":2017,"no":13,"country":"한국","designer":"권민호, 이수연（Kwon Minho, Lee Suyeon）","title":"그녀의 기록（Her records）","file":"5_13.jpg"},
{"yr":2017,"no":14,"country":"한국","designer":"김규호（Kim Kyuho）","title":"몸과 포르노그래피（Body and pornography）","file":"5_14.jpg"},
{"yr":2017,"no":15,"country":"한국","designer":"이건정 (Lee Gunjung)","title":"Gif for Left Handed Gill (Typeface Design : Kwon Youngchan)","file":"5_15.jpg"},
{"yr":2017,"no":16,"country":"한국","designer":"박신우 (Park Shinwoo)","title":"눈동자 유닛 (Eyeball Unit)","file":"5_16.jpg"},
{"yr":2017,"no":17,"country":"한국","designer":"정새우（Shrimp Chung）","title":"순도100% 남자의 눈물（100% PURE MALE TEARS）","file":"5_17.jpg"},
{"yr":2017,"no":18,"country":"한국","designer":"송민호（Song Minoh）","title":"Death Blossom What Are We Waiting For? Chapter 1. 6 Chapter 2. Min Chapter 3. Gabriel","file":"5_18.jpg"},
{"yr":2017,"no":19,"country":"한국","designer":"서희선 (Seo Heesun)","title":"ㅍㄷㅍㄷ（Flap Flap）","file":"5_19.jpg"},
{"yr":2017,"no":20,"country":"한국","designer":"권기영（Kwon Kiyoung）","title":"가위바위보（Rock-Paper-Scissors）","file":"5_20.jpg"},
{"yr":2017,"no":21,"country":"한국","designer":"양지은（Yang Jieun）","title":"Famous_Movie_Quotes_Meme_Django","file":"5_21.jpg"},
{"yr":2017,"no":22,"country":"한국","designer":"박철희（Park Chulhui）","title":"한글 레터링 모듈화（Hangul Lettering Module）","file":"5_22.jpg"},
{"yr":2017,"no":23,"country":"한국","designer":"조중현（Cho joonghyun）","title":"제목 없음（Untitled）","file":"5_23.jpg"},
{"yr":2017,"no":24,"country":"한국","designer":"김윤겸（Kim Yoongyeom）","title":"제목 없음（Untitled）","file":"5_24.jpg"},
{"yr":2017,"no":25,"country":"한국","designer":"황석원（Hwang Seogwon）","title":"비트（Bit）","file":"5_25.jpg"},
{"yr":2017,"no":26,"country":"한국","designer":"김보휘（Kim Bohuy）","title":"히릿（HIRRIT）","file":"5_26.jpg"},
{"yr":2017,"no":27,"country":"한국","designer":"함효정（Hahm Hyojung）","title":"Iamblue.gif, Serious Django.gif","file":"5_27.jpg"},
{"yr":2017,"no":28,"country":"한국","designer":"김현진（Jenny Kim）","title":"포커스（Focus ）","file":"5_28.jpg"},
{"yr":2017,"no":29,"country":"한국","designer":"김성구（Sung Kim）","title":"허 지부장의 딸（Huh’s-Daughter）","file":"5_29.jpg"},
{"yr":2017,"no":30,"country":"한국","designer":"프라울 (Praoul)","title":"아나토미 알파벳 (Anatomy Alphabet)","file":"5_30.jpg"},
{"yr":2017,"no":31,"country":"한국","designer":"김정활（Kim Junghwal）","title":"화질구지（Whajill Goojie）","file":"5_31.jpg"},
{"yr":2017,"no":32,"country":"한국","designer":"이유진（Lee Yujin）","title":"로드 트립（Road Trip）","file":"5_32.jpg"},
{"yr":2017,"no":33,"country":"한국","designer":"하형원（Ha Hyeongwon）","title":"<:3 )~~","file":"5_33.jpg"},
{"yr":2017,"no":34,"country":"한국","designer":"임원우(Lim Wonu)","title":"Electric Shock","file":"5_34.jpg"},
{"yr":2017,"no":35,"country":"한국","designer":"최정은 (Choe Jeongeun)","title":"ㅇㄷㅌㅌㅌ.gif (W DTTT.gif)","file":"5_35.jpg"},
{"yr":2017,"no":36,"country":"한국","designer":"임솔(Lim Sol）","title":"Wom","file":"5_36.jpg"},
{"yr":2017,"no":37,"country":"한국","designer":"박태석（Park Taeseok）","title":"G2_14_01","file":"5_37.jpg"},
{"yr":2017,"no":38,"country":"한국","designer":"전다운（Jeon Dawoon）","title":"콤비（Combination）","file":"5_38.jpg"},
{"yr":2017,"no":39,"country":"한국","designer":"권진주（Kwon Jinju）","title":"그린 비트 볼（Green Beat Ball）","file":"5_39.jpg"},
{"yr":2017,"no":40,"country":"한국","designer":"양민영（Yang Minyoung）","title":"우는 남자（No Man No Cry）","file":"5_40.jpg"},
{"yr":2017,"no":41,"country":"한국","designer":"이소현（Lee Sohyeon）","title":"성실한 학생.gif（good student.gif）","file":"5_41.jpg"},
{"yr":2017,"no":42,"country":"한국","designer":"윤충근（Yoon Choonggeun）","title":"성실한 학생.gif（good student.gif）","file":"5_42.jpg"},
{"yr":2017,"no":43,"country":"한국","designer":"민진아（Min Jinah）","title":"뷰티풀 보이즈（Beautiful Boys）","file":"5_43.jpg"},
{"yr":2017,"no":44,"country":"한국","designer":"원성연（Won Sungyeon）","title":"움짤 테스트1（Umjjal Test 1）","file":"5_44.jpg"},
{"yr":2017,"no":45,"country":"한국","designer":"김깊은（Kim Gipeun）","title":"제목 없음（Untitled）","file":"5_45.jpg"},
{"yr":2017,"no":46,"country":"한국","designer":"OOO","title":"충격 (Shock), 북실북실（Shaggy Shaggy）","file":"5_46.jpg"},
{"yr":2017,"no":47,"country":"한국","designer":"최지욱（Choi Jeeook）","title":"동공지진（Pupil Earthquake）","file":"5_47.jpg"},
{"yr":2017,"no":48,"country":"한국","designer":"이일주（Lee Ilju）","title":"기계 부품으로서의 삶_변형（Life As a Machine Element_Reduction）","file":"5_48.jpg"},
{"yr":2017,"no":49,"country":"한국","designer":"유재완（Yu Jaewan）","title":"스톱,해머 타임 !（Stop, Hammer Time!）","file":"5_49.jpg"},
{"yr":2017,"no":50,"country":"한국","designer":"한나은（Han Naeun）","title":"불특정A, 감시자A（Unspecific A, Surveilant A）","file":"5_50.jpg"},
{"yr":2017,"no":51,"country":"한국","designer":"이지희（Lee Jihee）","title":"제목 없음（Untitled）","file":"5_51.jpg"},
{"yr":2017,"no":52,"country":"한국","designer":"홍동오（Hong Dongoh）","title":"스포일러（Spoiler）","file":"5_52.jpg"},
{"yr":2017,"no":53,"country":"한국","designer":"도연경（Doe Yeonkyeong）","title":"내가 사는 세계（The Universe I Live in）","file":"5_53.jpg"},
{"yr":2017,"no":54,"country":"한국","designer":"윤현학（Yoon Ted Hyunhak）","title":"I DO NOT WANT TO GET MEMED ON","file":"5_54.jpg"},
{"yr":2017,"no":55,"country":"한국","designer":"백철훈（Baek Cheolhun）","title":"빌리 진（Billie Jean）","file":"5_55.jpg"},
{"yr":2017,"no":56,"country":"한국","designer":"오연진（Oh Yeonjin）","title":"쿼드 루틴（Quad routine）","file":"5_56.jpg"},
{"yr":2017,"no":57,"country":"한국","designer":"윤진（Yoon Jin）","title":"#깜빡（#Blink）","file":"5_57.jpg"},
{"yr":2017,"no":58,"country":"한국","designer":"이산하（Lee Sanha）","title":"관찰（Observation）","file":"5_58.jpg"},
{"yr":2017,"no":59,"country":"한국","designer":"박윤수（Park Yoonsoo）","title":"아이 컨택（EYE CONTACT）","file":"5_59.jpg"},
{"yr":2017,"no":60,"country":"한국","designer":"이도희（Lee Dohee）","title":"제목 없음（Untitled）","file":"5_60.jpg"},
{"yr":2017,"no":61,"country":"한국","designer":"김재하（Kim Jaeha）","title":"0과1（0 and 1）","file":"5_61.jpg"},
{"yr":2017,"no":62,"country":"한국","designer":"이윤서（Lee Yunseo）","title":"디더（Dither）","file":"5_62.jpg"},
{"yr":2017,"no":63,"country":"한국","designer":"유지연（Yoo Jiyeon）","title":"#minus9frames #r255g84 #zoomin #0.5seconds #resizing","file":"5_63.jpg"},
{"yr":2017,"no":64,"country":"한국","designer":"윤미원（Yoon Miwon）","title":"제목 없음（Untitled）","file":"5_64.jpg"},
{"yr":2017,"no":65,"country":"한국","designer":"조화라（Jo Hwara）","title":"기록- A（Record-A）","file":"5_65.jpg"},
{"yr":2017,"no":66,"country":"한국","designer":"손아용（Son Ayong）","title":"손（Hand）","file":"5_66.jpg"},
{"yr":2017,"no":67,"country":"한국","designer":"류우영（Ryu Uyeong）","title":"없음（None）","file":"5_67.jpg"},
{"yr":2017,"no":68,"country":"한국","designer":"김나래（Kim Narae）","title":"몰카,찍지마세요 !（Hidden Camera, Don’t take it!）","file":"5_68.jpg"},
{"yr":2017,"no":69,"country":"한국","designer":"리호（Lee ho）","title":"밈스 터치（MeME’s Touch）","file":"5_69.jpg"},
{"yr":2017,"no":70,"country":"한국","designer":"이수진（Lee Soojin）","title":"제목 없음（Untitled）","file":"5_70.jpg"},
{"yr":2017,"no":71,"country":"한국","designer":"김홍（Kim Hong）","title":"제목 없음（Untitled）","file":"5_71.jpg"},
{"yr":2017,"no":72,"country":"한국","designer":"김은하（Kim Eunha）","title":"제목 없음（Untitled）","file":"5_72.jpg"},
{"yr":2017,"no":73,"country":"한국","designer":"김승태（Kim Seungtae）","title":"제목 없음（Untitled）","file":"5_73.jpg"},
{"yr":2017,"no":74,"country":"한국","designer":"조소희（Cho Sohee）","title":"정확한 워딩（Correct Wording）","file":"5_74.jpg"},
{"yr":2017,"no":75,"country":"한국","designer":"최재훈（Werk）","title":"왼쪽-중간-오른쪽（Lefty-Middle-Righty ）","file":"5_75.jpg"},
{"yr":2017,"no":76,"country":"한국","designer":"김태희（Kim Taehee）","title":"부티 워크（booty wurk）","file":"5_76.jpg"},
{"yr":2017,"no":77,"country":"한국","designer":"강세아（Kang Se-a）","title":"상상 그 이상의 것（More Than You Imagine）","file":"5_77.jpg"},
{"yr":2017,"no":78,"country":"한국","designer":"이정은（Lee Jungeun）","title":"제목 없음（Untitled）","file":"5_78.jpg"},
{"yr":2017,"no":79,"country":"한국","designer":"윤지연（Yun Jiyeon）","title":"흐린 눈（Blurred Eyes）","file":"5_79.jpg"},
{"yr":2017,"no":80,"country":"한국","designer":"멜트미러（MELTMIRROR）","title":"논 안티에일리어싱（Non Anti-Aliasing）","file":"5_80.jpg"},
{"yr":2017,"no":81,"country":"한국","designer":"김희애（Fhuiae Kim）","title":"지프（dgif）","file":"5_81.jpg"},
{"yr":2017,"no":82,"country":"한국","designer":"김유리（Kim Eury）","title":"펀츠 펀츠（A Punch Punch）","file":"5_82.jpg"},
{"yr":2017,"no":83,"country":"한국","designer":"이화영（Lee Hwayoung）","title":"안구（EYEBALLS）","file":"5_83.jpg"},
{"yr":2017,"no":84,"country":"한국","designer":"이성철（Lee Seongcheol）","title":"댄스（Dance）","file":"5_84.jpg"},
{"yr":2017,"no":85,"country":"한국","designer":"강심지（Simjiuh）","title":"영원（Eternal）","file":"5_85.jpg"},
{"yr":2017,"no":86,"country":"한국","designer":"황정아（Hwang Jungah）","title":"고요 속의 외침（Cry in the Silence）","file":"5_86.jpg"},
{"yr":2017,"no":87,"country":"한국","designer":"임하영（Im Hayoung）","title":"깜빡（Blink）","file":"5_87.jpg"},
{"yr":2017,"no":88,"country":"한국","designer":"김지하（Kim Jiha）","title":"밈은 또 다른 밈이다.（A Meme Is Another Meme.）","file":"5_88.jpg"},
{"yr":2017,"no":89,"country":"한국","designer":"이희승（Lee Heeseung）","title":"눈이 먼（Blinded）","file":"5_89.jpg"},
{"yr":2017,"no":90,"country":"한국","designer":"박미화（Park Meehwa）","title":"제목 없음（Untitled）","file":"5_90.jpg"},
{"yr":2017,"no":91,"country":"한국","designer":"김혜수（Kim Hyesu）","title":"변신 마법소년 !（POP! Magical Man）","file":"5_91.jpg"},
{"yr":2017,"no":92,"country":"한국","designer":"성우진（Seung Uzin）","title":"눈깜빡（EYEBLINK）","file":"5_92.jpg"},
{"yr":2017,"no":93,"country":"한국","designer":"조은아（Cho Eunah）","title":"미메시스.gif（Mimesis.gif）","file":"5_93.jpg"},
{"yr":2017,"no":94,"country":"한국","designer":"김국한（Kim Gukhan）","title":"우린 제법 어울리고 또 멋져 (1)-(5) ","file":"5_94.jpg"},
{"yr":2017,"no":95,"country":"한국","designer":"차태현（Cha Taehyeon）","title":"제목 없음（Untitled）","file":"5_95.jpg"},
{"yr":2017,"no":96,"country":"한국","designer":"김하은（Kim Haeun）","title":"순간（Moment）","file":"5_96.jpg"},
{"yr":2017,"no":97,"country":"한국","designer":"이상균（Lee Sanggyun）","title":"1+1=? ","file":"5_97.jpg"},
{"yr":2017,"no":98,"country":"한국","designer":"신인아（Shin In-ah）","title":"25B","file":"5_98.jpg"},
{"yr":2017,"no":99,"country":"한국","designer":"홍태화（Hong Taehwa）","title":"RGB박수（RGB Clap）","file":"5_99.jpg"},
{"yr":2017,"no":100,"country":"한국","designer":"한승희（Han Seunghee）","title":"일주일（Week）","file":"5_100.jpg"},
{"yr":2017,"no":101,"country":"한국","designer":"한만오（Han Mano）","title":"폭발（Explosion）","file":"5_101.jpg"},
{"yr":2017,"no":102,"country":"한국","designer":"진한솔（Jin Hansol）","title":"二 重 人 格（Split-Personality）","file":"5_102.jpg"},
{"yr":2017,"no":103,"country":"한국","designer":"이송은（Lara Lee）","title":"Map.gif","file":"5_103.jpg"},
{"yr":2017,"no":104,"country":"한국","designer":"성중만（Sung Jungman）","title":"제목 없음（Untitled）","file":"5_104.jpg"},
{"yr":2017,"no":105,"country":"한국","designer":"이경진（Lee Kyungjin）","title":"제목 없음（Untitled）","file":"5_105.jpg"},
{"yr":2017,"no":106,"country":"한국","designer":"김리원（Kim Riwon）","title":"그림자 놀이（Shadow Play）","file":"5_106.jpg"},
{"yr":2017,"no":107,"country":"한국","designer":"조형석（Hyung Cho）","title":"유실물（Lost）","file":"5_107.jpg"},
{"yr":2017,"no":108,"country":"한국","designer":"류경호（Ryu Kyungho）","title":"바디 라인（Body Line）","file":"5_108.jpg"},
{"yr":2017,"no":109,"country":"한국","designer":"실키（Silkidoodle）","title":"돌아서기만 해도 남는 흔적（Trace even Turns Away）","file":"5_109.jpg"},
{"yr":2017,"no":110,"country":"한국","designer":"양효정（Yang Hyojung）","title":"재생산의 도구（Tool of Reproduction）","file":"5_110.jpg"},
{"yr":2017,"no":111,"country":"한국","designer":"김미리내（Kim Mirinae）","title":"엑스-본（X-Bone）","file":"5_111.jpg"},
{"yr":2017,"no":112,"country":"한국","designer":"권경림（Kwon Kyunglim）","title":"엉엉（Eong-Eong）","file":"5_112.jpg"},
{"yr":2017,"no":113,"country":"한국","designer":"김한솔（Sol Kim）","title":"부유하는 세포들（Floating Cells ）","file":"5_113.jpg"},
{"yr":2017,"no":114,"country":"한국","designer":"도한결（Do Hankyeol）","title":"노 크라이 노 우먼（NO CRY NO WOMAN）","file":"5_114.jpg"},
{"yr":2017,"no":115,"country":"한국","designer":"두루미와날치（Durumiwanalchi）","title":"오프 사이트（Off Site）","file":"5_115.jpg"},
{"yr":2017,"no":116,"country":"한국","designer":"유원선（Yu Wonseon）","title":"위글위글（Wiggle Wiggle）","file":"5_116.jpg"},
{"yr":2017,"no":117,"country":"한국","designer":"나하나（Na Hana）","title":"아스키 이모지（ASCII EMOJI）","file":"5_117.jpg"},
{"yr":2017,"no":118,"country":"한국","designer":"이규찬（Lee Kyuchan）","title":"무술영화 주인공들（Main Characters of Martial Arts Movie）","file":"5_118.jpg"},
{"yr":2017,"no":119,"country":"한국","designer":"박찬욱（Park Chanuk）","title":"Spam.gif","file":"5_119.jpg"},
{"yr":2017,"no":120,"country":"한국","designer":"김은서（Kim Eunseo）","title":"뭔가 짜증나네（Something Annoying）","file":"5_120.jpg"},
{"yr":2017,"no":121,"country":"한국","designer":"이동현（Lee Donghyun）","title":"내버려둔 것들（Dumped Things）","file":"5_121.jpg"},
{"yr":2017,"no":122,"country":"한국","designer":"주지민（Ju Jimin）","title":"돌기（Oddity）","file":"5_122.jpg"},
{"yr":2017,"no":123,"country":"한국","designer":"김연미（Kim Yeonmi）","title":"90%천사（90% Angel）","file":"5_123.jpg"},
{"yr":2017,"no":124,"country":"한국","designer":"빠키 (Vakki)","title":"우리는 매일 마주한다 (We Face Every Day)","file":"5_124.jpg"},
{"yr":2017,"no":125,"country":"한국","designer":"배민기 (Bae Minkee)","title":"풀 스케일 피지컬 엑서사이즈 (Full-scale physical exercise)","file":"5_125.jpg"},
{"yr":2017,"no":126,"country":"한국","designer":"민병걸 (Min Byunggeol)","title":"깃발장 (The Chest of Flags)","file":"5_126.jpg"},
{"yr":2017,"no":127,"country":"한국","designer":"김형재, 홍은주 (Kim Hyungjae, Hong Eunjoo)","title":"한국인이 사랑하는 ! (Koreans’ Favorite!)","file":"5_127.jpg"},
{"yr":2017,"no":128,"country":"일본","designer":"나가시마 리카코 (Nagashima Rikako)","title":"태양은 우리에게 전한다 (The Sun tells us)","file":"5_128.jpg"},
{"yr":2017,"no":129,"country":"한국","designer":"심대기, 심효준 (Shim Daeki, Shim Hyojun)","title":"019284","file":"5_129.jpg"},
{"yr":2017,"no":130,"country":"일본","designer":"오쿠무라 유키마사 (Okumura Yukimasa)","title":"오쿠무라 유키마사 디자인의 궤적 (Trajectory of Okumura Yukimasa’s Designs)","file":"5_130.jpg"},
{"yr":2017,"no":131,"country":"한국","designer":"김장우 (Kim Jangwoo)","title":"공예 이야기 (Craft Narrative)","file":"5_131.jpg"},
{"yr":2017,"no":132,"country":"일본","designer":"다이니폰 타입 조합 (Dainippon Type Organization)","title":"타입 / 문자 (Type/Character)","file":"5_132.jpg"},
{"yr":2017,"no":133,"country":"일본","designer":"무라마츠 타케히코 (Muramatsu Takehiko)","title":"얼굴 (Face","file":"5_133.jpg"},
{"yr":2017,"no":134,"country":"한국","designer":"박금준 (Park Kumjun)","title":"SOUL304","file":"5_134.jpg"},
{"yr":2017,"no":135,"country":"중국","designer":"베니 아우 (Benny Au)","title":"자유 (Freedom","file":"5_135.jpg"},
{"yr":2017,"no":136,"country":"일본","designer":"사이토 히로시 (Saito Hiroshi)","title":"인간관계 (Connection","file":"5_136.jpg"},
{"yr":2017,"no":137,"country":"일본","designer":"시로시타 사오리 (Shiroshita Saori)","title":"뒤죽박죽 (Wischiwaschi","file":"5_137.jpg"},
{"yr":2017,"no":138,"country":"한국","designer":"안삼열 (Ahn Samyeol)","title":"a-펭귄 (a-penguin","file":"5_138.jpg"},
{"yr":2017,"no":139,"country":"일본","designer":"야스다 타카히로 (Yasuda Takahiro)","title":"나타남 (EMERGE","file":"5_139.jpg"},
{"yr":2017,"no":140,"country":"일본","designer":"에토 타카히로 (Eto Takahiro)","title":"자 (子 ) / 자체 (子 體 ) / 체 (體 ) (Type/Type Body/Body","file":"5_140.jpg"},
{"yr":2017,"no":141,"country":"일본","designer":"타카야 렌 (Takaya Ren)","title":"JAGDA신인 디자이너 수상작 전시회2012 (JAGDA New Designer Awards Exhibition 2012)","file":"5_141.jpg"},
{"yr":2017,"no":142,"country":"중국","designer":"왕유안 (Wang Yuan)","title":"年 년 / 月 월 / 日 일 (Year / Month / Day)","file":"5_142.jpg"},
{"yr":2017,"no":143,"country":"한국","designer":"이경수 (Lee Kyeongsoo)","title":"오직 발견되었을 때만 드러나는 진실들이 있다. (There are truths that can only be revealed when they are discovered.)","file":"5_143.jpg"},
{"yr":2017,"no":144,"country":"한국","designer":"채병록（Chae Byungrok）","title":"자리와 선 (Meridian Channels)","file":"5_144.jpg"},
{"yr":2017,"no":145,"country":"한국","designer":"최종열 (Choi Jongyol)","title":"낭만적 유기체 (Romantic Organism)","file":"5_145.jpg"},
{"yr":2017,"no":146,"country":"일본","designer":"코노 사토시 (Kono Satoshi)","title":"언어가 없는 세계 (Wordless World)","file":"5_146.jpg"},
{"yr":2017,"no":147,"country":"일본","designer":"코스기 코이치 (Kosugi Koichi)","title":"기억의 궤적 (The Trajectory of Memory)","file":"5_147.jpg"},
{"yr":2017,"no":148,"country":"한국","designer":"크리스 로 (Chris Ro)","title":"여기, 여기. (Here. Here.)","file":"5_148.jpg"},
{"yr":2017,"no":149,"country":"일본","designer":"하토리 카즈나리 (Hattori Kazunari)","title":"버닝 A (Burning A)","file":"5_149.jpg"},
{"yr":2017,"no":150,"country":"중국","designer":"한웬빈 (Han Wenbin)","title":"웃고 살찌운다 (Laugh and grow fat)","file":"5_150.jpg"},
{"yr":2017,"no":151,"country":"중국","designer":"허이이양 (Hei Yiyang)","title":"선전 패션 위크 : 만화경 (Shenzhen Fashion Week : Kaleidoscope)","file":"5_151.jpg"},
{"yr":2017,"no":152,"country":"중국","designer":"허젠핑 (He Jianping)","title":"바나나 (Banana)","file":"5_152.jpg"},
{"yr":2017,"no":153,"country":"한국","designer":"김영나 (Na Kim)","title":"T v. 9 : 패턴 (SET v.9 : patterns)","file":"5_153.jpg"},
{"yr":2017,"no":154,"country":"한국","designer":"오래오 스튜디오 (Ore-oh! Studio)","title":"버스 정류장 고유 포스터 (Bus Shelter ID Poster)","file":"5_154.jpg"},
{"yr":2017,"no":155,"country":"한국","designer":"오디너리피플 (Ordinary People)","title":"연결하는 공간을 위한 다섯 단어 (Five words for connecting spaces)","file":"5_155.jpg"},
{"yr":2017,"no":156,"country":"한국","designer":"권아주, 장윤정 (Kwon Ahju, Jang Yoonjung)","title":"역삼동, 여성 (Yeoksam-dong, Women)","file":"5_156.jpg"},
{"yr":2017,"no":157,"country":"한국","designer":"권영찬 (Kwon Youngchan)","title":"국제 타이포그래피 비엔날레 (International Typography Biennale)","file":"5_157.jpg"},
{"yr":2017,"no":158,"country":"한국","designer":"김가든 (Kimgarden)","title":"창 신 동 (Changsin-dong)","file":"5_158.jpg"},
{"yr":2017,"no":159,"country":"한국","designer":"김경림 (Kim Kyounglim)","title":"야 누 스 의 도 시 (City of Janus)","file":"5_159.jpg"},
{"yr":2017,"no":160,"country":"한국","designer":"플롯 (p-l-o-t)","title":"단 위 (Unit)","file":"5_160.jpg"},
{"yr":2017,"no":161,"country":"한국","designer":"김동훈, 김도현 (Kim Donghoon, Kim Dohyen)","title":"지 명 유 희 (Word Game with Place Names)","file":"5_161.jpg"},
{"yr":2017,"no":162,"country":"한국","designer":"김소미 (Kim Somi)","title":"미래 가치 (Future Value)","file":"5_162.jpg"},
{"yr":2017,"no":163,"country":"한국","designer":"김의래와 특정다수 (Kim Euirae and A Certain People)","title":"다섯 가지의 정동 (Jung-dong)","file":"5_163.jpg"},
{"yr":2017,"no":164,"country":"한국","designer":"물질과 비물질 (Waterain)","title":"불 광 (Bulgwang)","file":"5_164.jpg"},
{"yr":2017,"no":165,"country":"한국","designer":"타불라라사 (Tabula Rasa)","title":"서울랜드 (SEOULand)","file":"5_165.jpg"},
{"yr":2017,"no":166,"country":"한국","designer":"김한솔, 조혜연 (Kim Hansol, Cho Hyeyeon)","title":"서울 흐르기 (Streaming along Seoul)","file":"5_166.jpg"},
{"yr":2017,"no":167,"country":"한국","designer":"문민주 (Moon Minjoo)","title":"공중정원 난지 (Hanging Garden Rejectamenta)","file":"5_167.jpg"},
{"yr":2017,"no":168,"country":"한국","designer":"하와이안샐러드 (Hawaiiansalad)","title":"혜화를 혜화이게 하는 것 (Things that Make Hyehwa)","file":"5_168.jpg"},
{"yr":2017,"no":169,"country":"한국","designer":"3분1초 (3m1s)","title":"이상한 악보 (Music of Yun Isang)","file":"5_169.jpg"},
{"yr":2017,"no":170,"country":"한국","designer":"둘셋 (TWOTHREE)","title":"불완전한 교차 (Incomplete Cross)","file":"5_170.jpg"},
{"yr":2017,"no":171,"country":"한국","designer":"석재원 (Seok Jaewon)","title":"카모 시티 (Camo City)","file":"5_171.jpg"},
{"yr":2017,"no":172,"country":"한국","designer":"손혜인 (Son Heiin)","title":"시시 (視 詩 ) 서울 (SeeSeeSeoul)","file":"5_172.jpg"},
{"yr":2017,"no":173,"country":"한국","designer":"오와이이 (OYE)","title":"우연한 산책, 익숙한 산책 (Accidental walk, Familiar walk)","file":"5_173.jpg"},
{"yr":2017,"no":174,"country":"한국","designer":"유명상 (Yu Myungsang)","title":"동네 숲 (A Small Forest)","file":"5_174.jpg"},
{"yr":2017,"no":175,"country":"한국","designer":"유윤석 (Yoo Yoonseok)","title":"구민의 노래 (Autonomous District Anthems)","file":"5_175.jpg"},
{"yr":2017,"no":176,"country":"한국","designer":"선데이 (5unday)","title":"서울에서 살고 있다 (Live in Seoul)","file":"5_176.jpg"},
{"yr":2017,"no":177,"country":"한국","designer":"텍스트 (TEXT)","title":"도시 속 움직임 (Gestures in Urban Space)","file":"5_177.jpg"},
{"yr":2017,"no":178,"country":"한국","designer":"이천성 (Lee Cheonseong)","title":"쌓이는 것들, 벗겨지는 것들 (Pile and peel)","file":"5_178.jpg"},
{"yr":2017,"no":179,"country":"한국","designer":"스팍스에디션 (Sparks Edition)","title":"정릉, 에너지 순환의 도시 (Energy Circulation City, Jeongneung)","file":"5_179.jpg"},
{"yr":2017,"no":180,"country":"한국","designer":"정영훈, 구모아 (Jung Younghun, Ku Moa)","title":"같은 공간, 다른 연결 : 남대문 시장 타이포그래피 (Same Space, Another Connection : Namdaemun Market Typography)","file":"5_180.jpg"},
{"yr":2017,"no":181,"country":"한국","designer":"정성훈, 정연지 (Jung Sunghun, Jeoung Yeonji)","title":"버티고개와 까치산 (New Town in the City)","file":"5_181.jpg"},
{"yr":2017,"no":182,"country":"한국","designer":"킽 (Kit)","title":"서울 지하도 여행 (A Trip to Underpass in Seoul)","file":"5_182.jpg"},
{"yr":2017,"no":183,"country":"한국","designer":"코우너스 (Corners)","title":"우리 동네 낱말 퀴즈 (Our Neighborhood)","file":"5_183.jpg"},
{"yr":2017,"no":184,"country":"한국","designer":"더블디 (Double-D)","title":"발견된, 완벽한 후기 (The Found Perfect Review)","file":"5_184.jpg"},
{"yr":2017,"no":185,"country":"한국","designer":"김광철, 이마빈(Kim Kwangchul, Lee Marvin )","title":"독립 출판 프로젝트,《몸사전》(Independent Publishing Project Body Dictionary)","file":"5_185.jpg"},
{"yr":2017,"no":186,"country":"한국","designer":"박연주 (Park Yeonjoo)","title":"리서치 프로젝트,《터치타입》 & 《낫더타입》 (Research Project Touch Type & Knot the Type)","file":"5_186.jpg"},
{"yr":2017,"no":187,"country":"한국","designer":"윤율리, 이마빈(Yoon Juli, Lee Marvin)","title":"아카이브 프로젝트, 매거진 (Archive Project, Magazine)","file":"5_187.jpg"},
{"yr":2017,"no":188,"country":"한국","designer":"오디너리피플 (Ordinary People)","title":"《타이포잔치 2017》아이덴티티 디자인 (Typojanchi 2017 Identity Design)","file":"5_188.jpg"},
{"yr":2017,"no":189,"country":"한국","designer":"문화수도 (Capital of Culture)","title":"《타이포잔치2017》사진, 영상 기록 (Typojanchi 2017 Photo & Video Record)","file":"5_189.jpg"},
{"yr":2017,"no":190,"country":"한국","designer":"COM ","title":"《타이포잔치 2017》전시 공간 디자인 (Typojanchi 2017 Exhibition Space Design)","file":"5_190.jpg"},
{"yr":2017,"no":191,"country":"한국","designer":"레벨나인 (Rebel9)","title":"《타이포잔치2017》웹사이트 (Typojanchi 2017 Website)","file":"5_191.jpg"},
{"yr":2017,"no":192,"country":"한국","designer":"제로랩 (Zero Lab)","title":"《타이포잔치 2017》연계 전시 공간 디자인 (Typojanchi 2017 Connected Exhibition Space Design)","file":"5_192.jpg"},
{"yr":2017,"no":193,"country":"한국","designer":"현대자동차 (Hyundai Motors)","title":"현대자동차 ×《타이포잔치》(Hyundai Motors X Typojanchi)","file":"5_193.jpg"},
{"yr":2017,"no":194,"country":"한국","designer":"두성종이 (Doosung Paper)","title":"우리 안의 바람, 가벼움과 부드러움 (The wind inside us : Lightness and softness)","file":"5_194.jpg"}]